hass_client/__init__.py
hass_client/client.py
hass_client/const.py
hass_client/exceptions.py
hass_client/models.py
hass_client/utils.py
hass_client-2.0.0.dist-info/LICENSE
hass_client-2.0.0.dist-info/METADATA
hass_client-2.0.0.dist-info/WHEEL
hass_client-2.0.0.dist-info/top_level.txt
hass_client-2.0.0.dist-info/RECORD
